README.txt
setup.py
collective/__init__.py
collective.searchweightings.egg-info/PKG-INFO
collective.searchweightings.egg-info/SOURCES.txt
collective.searchweightings.egg-info/dependency_links.txt
collective.searchweightings.egg-info/entry_points.txt
collective.searchweightings.egg-info/namespace_packages.txt
collective.searchweightings.egg-info/not-zip-safe
collective.searchweightings.egg-info/paster_plugins.txt
collective.searchweightings.egg-info/requires.txt
collective.searchweightings.egg-info/top_level.txt
collective/searchweightings/README.txt
collective/searchweightings/__init__.py
collective/searchweightings/adapters.py
collective/searchweightings/configure.zcml
collective/searchweightings/interfaces.py
collective/searchweightings/patches.py
collective/searchweightings/tests.py
docs/HISTORY.txt
docs/INSTALL.txt
docs/LICENSE.GPL
docs/LICENSE.txt