Metadata-Version: 1.0
Name: collective.searchweightings
Version: 1.1
Summary: Allow arbitrary adapters to be registered to weight search results differently
Home-page: http://svn.plone.org/svn/collective/
Author: Matt Hamilton
Author-email: matth@netsight.co.uk
License: GPL
Keywords: zope plone search index catalog
Platform: UNKNOWN
Classifier: Framework :: Plone
Classifier: Programming Language :: Python
